<DOMSymbolItem xmlns:xsi="http://www.w3.org/2001/XMLSchema-instance" xmlns="http://ns.adobe.com/xfl/2008/" name="linksbutton" itemID="4efcb4ef-000002c9" sourceLibraryItemHRef="Symbol 1" lastModified="1325184239">
  <timeline>
    <DOMTimeline name="linksbutton">
      <layers>
        <DOMLayer name="Layer 1" color="#4FFF4F" current="true" isSelected="true">
          <frames>
            <DOMFrame index="0" keyMode="9728">
              <elements>
                <DOMShape>
                  <fills>
                    <FillStyle index="1">
                      <SolidColor color="#0099FF"/>
                    </FillStyle>
                  </fills>
                  <edges>
                    <Edge fillStyle0="1" edges="!191 -25[0 -25 0 201!0 201|0 564!0 564[6 775 191 775!191 775|710 775!710 775[900 775 900 550!900 550|900 201!900 201[900 -20 717 -25!717 -25|191 -25"/>
                    <Edge cubics="!900 201(;900,54 839,-20 717,-25q900 201Q900 -20q717 -25)717,-25;"/>
                    <Edge cubics="!900 550(;900,550 900,201 900,201q900 550 900 201);"/>
                    <Edge cubics="!710 775(;836,775 900,700 900,550q710 775Q900 775q900 550);"/>
                    <Edge cubics="!191 -25(;64,-25 0,50 0,201q191 -25Q0 -25q0 201);"/>
                    <Edge cubics="!0 564(;5,706 69,775 191,775q0 564Q6 775q191 775);"/>
                    <Edge cubics="!191 775(;191,775 710,775 710,775q191 775 710 775);"/>
                    <Edge cubics="!0 201(0,201;0,201 0,564 0,564q0 201 0 564);"/>
                    <Edge cubics="!191 -25(;191,-25 717,-25 717,-25q191 -25 717 -25)717,-25;"/>
                    <Edge cubics="!884 2177(;884,2030 823,1956 701,1951q884 2177Q884 1956q701 1951)701,1951;"/>
                    <Edge cubics="!884 2526(;884,2526 884,2177 884,2177q884 2526 884 2177);"/>
                    <Edge cubics="!694 2751(;820,2751 884,2676 884,2526q694 2751Q884 2751q884 2526);"/>
                    <Edge cubics="!175 1951(;48,1951 -16,2026 -16,2177q175 1951Q-16 1951q-16 2177);"/>
                    <Edge cubics="!-16 2540(;-11,2682 53,2751 175,2751q-16 2540Q-10 2751q175 2751);"/>
                    <Edge cubics="!175 2751(;175,2751 694,2751 694,2751q175 2751 694 2751);"/>
                    <Edge cubics="!-16 2177(-16,2177;-16,2177 -16,2540 -16,2540q-16 2177 -16 2540);"/>
                    <Edge cubics="!175 1951(;175,1951 701,1951 701,1951q175 1951 701 1951)701,1951;"/>
                  </edges>
                </DOMShape>
                <DOMDynamicText name="linkstext" width="42.5" height="20" isSelectable="false">
                  <matrix>
                    <Matrix tx="2" ty="15.35"/>
                  </matrix>
                  <textRuns>
                    <DOMTextRun>
                      <characters>links</characters>
                      <textAttrs>
                        <DOMTextAttrs alignment="center" aliasText="false" rotation="true" lineSpacing="2.4" size="18" bitmapSize="360" face="ArialMT" fillColor="#FFFFFF"/>
                      </textAttrs>
                    </DOMTextRun>
                  </textRuns>
                </DOMDynamicText>
                <DOMDynamicText width="35" height="20" isSelectable="false">
                  <matrix>
                    <Matrix tx="5.35" ty="-1.35"/>
                  </matrix>
                  <textRuns>
                    <DOMTextRun>
                      <characters>&lt;/&gt;</characters>
                      <textAttrs>
                        <DOMTextAttrs alignment="center" aliasText="false" rotation="true" lineSpacing="2.4" size="18" bitmapSize="360" face="ArialMT" fillColor="#FFFFFF"/>
                      </textAttrs>
                    </DOMTextRun>
                  </textRuns>
                </DOMDynamicText>
              </elements>
            </DOMFrame>
          </frames>
        </DOMLayer>
      </layers>
    </DOMTimeline>
  </timeline>
</DOMSymbolItem>